LICENSE
README.md
setup.py
ExcelSheetIO/CellStyler.py
ExcelSheetIO/ColorPickers.py
ExcelSheetIO/ExcelReaderWriter.py
ExcelSheetIO/ExcelStyler.py
ExcelSheetIO/__init__.py
ExcelSheetIO.egg-info/PKG-INFO
ExcelSheetIO.egg-info/SOURCES.txt
ExcelSheetIO.egg-info/dependency_links.txt
ExcelSheetIO.egg-info/requires.txt
ExcelSheetIO.egg-info/top_level.txt