Metadata-Version: 2.1
Name: ExcelSheetIO
Version: 0.7
Summary: A Python package for efficient Excel sheet operations. Enables easy read/write functionality, data manipulation, and workflow automation. Ideal for handling both small and large datasets. Get started with ExcelSheetIO for a simplified data processing experience.
Home-page: https://pypi.org/project/ExcelSheetIO/
Author: Soumyajit Pan
Author-email: soumyajitmahi7@gmail.com
License: MIT
Keywords: excelsheetio,excel,excelreader,excelwriter,python,excel reader and writer,read excel data using python,write data in excel using python,excelsheetio
Platform: UNKNOWN
License-File: LICENSE
